[
    {
        "title": "Donald J Trump For President Rally",
        "date": "2015-09-14",
        "time": "6:00 PM",
        "location": "Dallas, TX",
        "url": "http://eventful.com/performers/donald-trump-/P0-001-000039021-2"
    },
    {
        "title": "Donald J Trump For President Rally",
        "date": "2015-09-21",
        "time": "7:00 PM",
        "location": "Mobile, Alabama",
        "url": "http://eventful.com/performers/donald-trump-/P0-001-000039021-2"
    },
    {
        "title": "Donald J Trump For President Rally",
        "date": "2015-09-28",
        "time": "7:00 PM",
        "location": "Mobile, Alabama",
        "url": "http://eventful.com/performers/donald-trump-/P0-001-000039021-2"
    },
    {
        "title": "Donald J Trump For President Rally",
        "date": "2015-09-29",
        "time": "7:00 PM",
        "location": "Mobile, Alabama",
        "url": "http://eventful.com/performers/donald-trump-/P0-001-000039021-2"
    }
]